pylings/__init__.py
pylings/__main__.py
pylings/config.py
pylings/constants.py
pylings/debug.py
pylings/exercises.py
pylings/init.py
pylings/pylings.py
pylings/theme.py
pylings/ui.py
pylings/utils.py
pylings/watcher.py
pylings/backups/00_intro/intro1.py
pylings/backups/01_variables/README.md
pylings/backups/01_variables/variables1.py
pylings/backups/01_variables/variables2.py
pylings/backups/01_variables/variables3.py
pylings/backups/01_variables/variables4.py
pylings/backups/01_variables/variables5.py
pylings/backups/02_data_structures/README.md
pylings/backups/02_data_structures/data_structures1.py
pylings/backups/02_data_structures/data_structures2.py
pylings/backups/02_data_structures/data_structures3.py
pylings/backups/02_data_structures/data_structures4.py
pylings/backups/03_functions/README.md
pylings/backups/03_functions/functions1.py
pylings/backups/03_functions/functions2.py
pylings/backups/03_functions/functions3.py
pylings/backups/03_functions/functions4.py
pylings/backups/03_functions/functions5.py
pylings/backups/04_conditionals/README.md
pylings/backups/04_conditionals/conditionals1.py
pylings/backups/04_conditionals/conditionals2.py
pylings/backups/04_conditionals/conditionals3.py
pylings/backups/04_conditionals/conditionals4.py
pylings/backups/05_loops/README.md
pylings/backups/05_loops/loops1.py
pylings/backups/06_oop/README.md
pylings/backups/06_oop/oop1.py
pylings/backups/06_oop/oop2.py
pylings/backups/06_oop/oop3.py
pylings/backups/07_quiz/README.md
pylings/backups/07_quiz/quiz1.py
pylings/backups/08_error_handling/README.md
pylings/backups/08_error_handling/errors1.py
pylings/backups/08_error_handling/errors2.py
pylings/backups/08_error_handling/errors3.py
pylings/backups/08_error_handling/errors4.py
pylings/backups/09_threading/README.md
pylings/backups/09_threading/threading1.py
pylings/backups/09_threading/threading2.py
pylings/backups/09_threading/threading3.py
pylings/config/config.toml
pylings/config/themes.toml
pylings-1.3.0.dist-info/licenses/LICENSE.md
pylings-1.3.0.dist-info/METADATA
pylings-1.3.0.dist-info/WHEEL
pylings-1.3.0.dist-info/entry_points.txt
pylings-1.3.0.dist-info/top_level.txt
pylings-1.3.0.dist-info/RECORD
