Metadata-Version: 2.4
Name: pylings
Version: 1.3.0
Summary: Python exercise trainer, inspired by rustlings.
Author-email: Seb Blair <s.blair@gre.ac.uk>
License-Expression: MIT
Project-URL: homepage, https://pypi.org/project/pylings/
Project-URL: Repository, https://github.com/CompEng0001/pylings
Project-URL: tracker, https://github.com/CompEng0001/pylings/issues
Classifier: Development Status :: 5 - Production/Stable
Classifier: Intended Audience :: Education
Classifier: Programming Language :: Python :: 3.10
Classifier: Programming Language :: Python :: 3.11
Classifier: Programming Language :: Python :: 3.12
Classifier: Programming Language :: Python :: 3.13
Classifier: Programming Language :: Python :: Implementation
Classifier: Operating System :: Microsoft :: Windows
Classifier: Operating System :: MacOS
Classifier: Operating System :: POSIX :: Linux
Classifier: Operating System :: Unix
Classifier: Topic :: Education
Requires-Python: >=3.10
License-File: LICENSE.md
Requires-Dist: textual==2.1.2
Requires-Dist: psutil==7.0.0
Requires-Dist: watchdog==6.0.0
Requires-Dist: rich==13.9.4
Requires-Dist: toml==0.10.2
Dynamic: license-file
